timelock_wasm_wrapper-0.0.2.dist-info/METADATA
timelock_wasm_wrapper-0.0.2.dist-info/WHEEL
timelock_wasm_wrapper/__init__.py
timelock_wasm_wrapper/timelock_wasm_wrapper.cpython-310-x86_64-linux-gnu.so
timelock_wasm_wrapper-0.0.2.dist-info/RECORD
