Metadata-Version: 2.3
Name: timelock_wasm_wrapper
Version: 0.0.2
Summary: Wasm bidings for the timelock encryption crate
Home-Page: https://idealabs.network
Author: Ideal Lab5 <hello@idealabs.network>
Author-email: Ideal Lab5 <hello@idealabs.network>
License: Apache-2.0
Project-URL: Source Code, https://github.com/ideal-lab5/timelock
